Metadata-Version: 2.1
Name: rabin
Version: 0.1.0
Summary: A simple Python module for generating Rabin signatures
Home-page: https://github.com/msinkec/python-rabin
Author: 
License: UNKNOWN
Keywords: rabin signatures cryptography encryption
Platform: UNKNOWN
